pycordViews/__init__.py
pycordViews/kit/__init__.py
pycordViews/kit/back.py
pycordViews/kit/confirm.py
pycordViews/kit/poll.py
pycordViews/menu/__init__.py
pycordViews/menu/errors.py
pycordViews/menu/menu.py
pycordViews/menu/selectMenu.py
pycordViews/modal/__init__.py
pycordViews/modal/easy_modal_view.py
pycordViews/modal/errors.py
pycordViews/multibot/__init__.py
pycordViews/multibot/bot.py
pycordViews/multibot/errors.py
pycordViews/multibot/multibot.py
pycordViews/multibot/process.py
pycordViews/pagination/__init__.py
pycordViews/pagination/errors.py
pycordViews/pagination/page.py
pycordViews/pagination/pagination_view.py
pycordViews/views/__init__.py
pycordViews/views/easy_modified_view.py
pycordViews/views/errors.py
pycordviews-1.3.8.0.dist-info/licenses/LICENSE
pycordviews-1.3.8.0.dist-info/METADATA
pycordviews-1.3.8.0.dist-info/WHEEL
pycordviews-1.3.8.0.dist-info/top_level.txt
pycordviews-1.3.8.0.dist-info/RECORD
